ghostwriter/__init__.py
ghostwriter/base.py
ghostwriter/ghostwriter.py
ghostwriter/project.py
ghostwriter/settings.py
ghostwriter/strings.py
ghostwriter/dockeronion/__init__.py
ghostwriter/dockeronion/dockeronion.py
ghostwriter/onionshare/__init__.py
ghostwriter/onionshare/onionshare.py
ghostwriter/web/__init__.py
ghostwriter/web/web.py
ghostwriter-0.1.data/scripts/ghostwriter
ghostwriter-0.1.data/scripts/ghostwriter-gui
ghostwriter_gui/__init__.py
ghostwriter_gui/ghostwriter_gui.py
ghostwriter_gui/logs_handler.py
ghostwriter_gui/logs_layout.py
ghostwriter_gui/menu_layout.py
ghostwriter_gui/open_project.py
ghostwriter_gui/project_layout.py
ghostwriter_gui/settings_panel.py
tests/__init__.py
tests/conftests.py
tests/test_ghost.py
usr/share/ghostwriter/version.txt
usr/share/ghostwriter/containers/website/Dockerfile
usr/share/ghostwriter/containers/website/default
usr/share/ghostwriter/containers/website/onion-entrypoint.sh
usr/share/ghostwriter/containers/website/tor/torrc
usr/share/ghostwriter/images/ghostwriter-grayscale.png
usr/share/ghostwriter/images/ghostwriter.png
usr/share/ghostwriter/images/ghostwriter.svg
usr/share/ghostwriter/locale/en.json
ghostwriter-0.1.dist-info/LICENSE
ghostwriter-0.1.dist-info/METADATA
ghostwriter-0.1.dist-info/WHEEL
ghostwriter-0.1.dist-info/top_level.txt
ghostwriter-0.1.dist-info/RECORD
