Metadata-Version: 2.1
Name: ghostwriter
Version: 0.1
Summary: GhostWriter lets you edit a website via lektor, a flexible and powerful static content management system for building complex and beautiful websites out of flat files - for people who do not want to make a  compromise between a CMS and a static blog engine. 
Home-page: https://github.com/hiromipaw/ghostwriter
Author: Hiro
Author-email: hiro@torproject.org
Maintainer: Hiro
Maintainer-email: hiro@torproject.org
License: GPL v3
Keywords: lektor,website,docker,container,ghostwriter,onionshare,onion,tor,anonymous,web server
Platform: UNKNOWN
Classifier: Programming Language :: Python :: 3
Classifier: Topic :: Software Development :: Code Generators
Classifier: Topic :: Security :: Cryptography
Classifier: License :: OSI Approved :: GNU General Public License v3 or later (GPLv3+)
Classifier: Intended Audience :: End Users/Desktop
Classifier: Operating System :: OS Independent
Classifier: Environment :: Web Environment
Classifier: Environment :: X11 Applications :: Qt
